{
  "1-10": {
    "10h - BA": {
      "cabecalhos": [
        "Prêmio",
        "Milhar",
        "Grupo",
        "Bicho"
      ],
      "dados": [
        {
          "Prêmio": "1º",
          "Milhar": "4146",
          "Grupo": "12",
          "Bicho": "Elefante"
        },
        {
          "Prêmio": "2º",
          "Milhar": "5714",
          "Grupo": "04",
          "Bicho": "Borboleta"
        },
        {
          "Prêmio": "3º",
          "Milhar": "8849",
          "Grupo": "13",
          "Bicho": "Galo"
        },
        {
          "Prêmio": "4º",
          "Milhar": "1665",
          "Grupo": "17",
          "Bicho": "Macaco"
        },
        {
          "Prêmio": "5º",
          "Milhar": "0939",
          "Grupo": "10",
          "Bicho": "Coelho"
        },
        {
          "Prêmio": "6º",
          "Milhar": "8574",
          "Grupo": "19",
          "Bicho": "Pavão"
        },
        {
          "Prêmio": "7º",
          "Milhar": "2338",
          "Grupo": "10",
          "Bicho": "Coelho"
        },
        {
          "Prêmio": "8º",
          "Milhar": "9610",
          "Grupo": "03",
          "Bicho": "Burro"
        },
        {
          "Prêmio": "9º",
          "Milhar": "4048",
          "Grupo": "12",
          "Bicho": "Elefante"
        },
        {
          "Prêmio": "10º",
          "Milhar": "9787",
          "Grupo": "22",
          "Bicho": "Tigre"
        }
      ],
      "frases": {},
      "acertos": {
        "Milhar": 0,
        "Centena": 0,
        "Dezena": 0,
        "Grupo": []
      },
      "resumo": "Palpites dados para esta extração: 1070, 1078, 1370, 1378, 1870, 1878, 3070, 3078, 3370, 3378, 3870, 3878, 4070, 4078, 4370, 4378, 4870, 4878, 5070, 5078, 5370, 5378, 5870, 5878, 6070, 6078, 6370, 6378, 6870, 6878, 7070, 7078, 7370, 7378, 7870, 7878, 8070, 8078, 8370, 8378, 8870, 8878, 9070, 9078, 9370, 9378, 9870, 9878"
    },
    "12h - BA": {
      "cabecalhos": [
        "Prêmio",
        "Milhar",
        "Grupo",
        "Bicho"
      ],
      "dados": [
        {},
        {},
        {},
        {},
        {},
        {},
        {},
        {},
        {},
        {}
      ],
      "frases": {},
      "acertos": {
        "Milhar": 0,
        "Centena": 0,
        "Dezena": 0,
        "Grupo": []
      },
      "resumo": ""
    }
  }
}